{
  "school": "聖グロリアーナ女学院",
  "tanks": [
    {
      "tank_id": "stgloriana-churchill-mk7",
      "name": "Mk.Ⅳ歩兵戦車チャーチルMk.Ⅶ",
      "assignment": "聖グロリアーナ女学院",
      "count": null,
      "description": "1940年にMk.Ⅳ歩兵戦車として制式採用され、41年から量産が開始された。当初は2ポンド戦車砲が搭載され後に6ポンド戦車砲に換装されて武装が強化された。Mk.Ⅶは75ｍｍ戦車砲を装備し最大装甲厚が152.4mmに強化された重武装タイプ。火炎放射戦車や戦車回収車、架橋戦車なども生産され、朝鮮戦争でも実戦投入され1960年代まで現役として活躍した。",
      "specs": {
        "国籍": "イギリス",
        "乗員": "5名",
        "エンジン": "ベドフォード 水平対向12気筒液冷ガソリン",
        "重量": "40.64t",
        "全長": "7.44m",
        "車体長": "7.44m",
        "全幅": "2.74m",
        "全高": "3.25m",
        "履帯幅": "55.8cm",
        "超壕能力": "3.7m",
        "渡渉水深": "0.9m",
        "変速機": "前進4速後進1速",
        "最高速度": "20.12km/h（路上）",
        "航続距離": "193km（路上）",
        "主砲": "37.5口径75mm戦車砲（主砲弾：84発）",
        "副武装": "7.92mmベサ重機関銃×2",
        "装甲": "19.05～152.4mm"
      }
    },
    {
      "tank_id": "stgloriana-centurion-a41",
      "name": "巡航戦車A41センチュリオン",
      "assignment": "聖グロリアーナ女学院",
      "count": null,
      "description": "第二次大戦までイギリスの戦車は、軽装甲高速の巡航戦車と重装甲低速の歩兵戦車の二本柱だったが、戦車の進歩に伴って重装甲重武装と機動力の両立が求められるようになった。重巡航戦車のA41は、チャーチルの優れた変速操向装置にミーティアエンジンを組み合わせ、地形把握性と整備性に優れたホルストマン式サスペンションを搭載。不整地での活動を重視することで、カタログスペック以上の機動性を発揮できた。",
      "specs": {
        "国籍": "イギリス",
        "乗員": "4名",
        "エンジン": "ロールスロイス・ミーティアMk.Ⅳ V型12気筒液冷ガソリン",
        "重量": "48.7t",
        "全長": "7.67m",
        "全幅": "3.37m",
        "全高": "2.81m",
        "履帯幅": "57.0cm",
        "超壕能力": "3.35m",
        "渡渉水深": "1.90m",
        "変速機": "前進5段後進2段",
        "最高速度": "34km/h（路上）",
        "航続距離": "96km",
        "主砲": "口径76.2mm砲 砲弾：70発",
        "副武装": "ベサ7.92mm機関銃×1",
        "装甲": "17～127mm"
      }
    },
    {
      "tank_id": "stgloriana-matilda-ii-mk3-4",
      "name": "Mk.Ⅱ歩兵戦車マチルダⅡMk.Ⅲ/Ⅳ",
      "assignment": "聖グロリアーナ女学院",
      "count": null,
      "description": "1936年度に英国陸軍が要求仕様を出し、37年に予算化された。味方の歩兵を敵戦車の攻撃から護ることを目的に開発された歩兵戦車。その重装甲は北アフリカ戦線でドイツ戦車の戦車砲に対して優位を保ち「戦場の女王」と称され、88ｍｍ高射砲以外で撃破することは困難だった。地雷除去戦車、火炎放射戦車、架橋戦車等にも改造され、第二次大戦の終戦まで使用された。",
      "specs": {
        "国籍": "イギリス",
        "乗員": "4名",
        "エンジン": "レイランドE148/149 V型6気筒液冷ディーゼル",
        "重量": "27.0t",
        "全長": "5.61m",
        "車体長": "5.61m",
        "全幅": "2.59m",
        "全高": "2.52m",
        "履帯幅": "35.5cm",
        "超壕能力": "2.1m",
        "渡渉水深": "0.9m",
        "変速機": "前進6速後進1速",
        "最高速度": "24.1km/h（路上）",
        "航続距離": "257km（路上）",
        "主砲": "50口径2ポンド砲（主砲弾：93発）",
        "副武装": "7.92mmベサ重機関銃×1",
        "装甲": "13～78mm"
      }
    },
    {
      "tank_id": "stgloriana-crusader-mk3",
      "name": "Mk.Ⅵ巡航戦車クルセイダーMk.Ⅲ",
      "assignment": "聖グロリアーナ女学院",
      "count": null,
      "description": "イギリスが開発した巡航戦車。快速性能を活かした機動戦を主任務としていた。主として北アフリカ戦線で活躍したが、主砲の2ポンド砲はやがて火力不足となった。Mk.Ⅲは主砲を6ポンド砲に換装して火力を強化したタイプ。もともと航空機用に開発されたエンジンがシリンダーを個別に本体にボルト止めする構造で、走行時の振動が大きい戦車用には向いておらずオイル漏れが多発した上に、チェーン駆動（のちにシャフト駆動に改良された）の冷却ファンなどにも故障が頻発した。",
      "specs": {
        "国籍": "イギリス",
        "乗員": "3名",
        "エンジン": "ナフィールド・リバティー V型 12気筒液冷ガソリン",
        "重量": "20.067t",
        "全長": "5.982m",
        "全幅": "2.642m",
        "全高": "2.235m",
        "最高速度": "44.26km/h（路上）",
        "航続距離": "161km",
        "主砲": "43口径6ポンド砲Mk.Ⅲ（主砲弾：65発）",
        "副武装": "7.92mmベサ重機関銃×1",
        "装甲": "13～78mm"
      }
    }
  ]
}
